hapi2/__init__.py
hapi2/version.py
hapi2/collect/__init__.py
hapi2/collect/jeanny3.py
hapi2/config/__init__.py
hapi2/config/config.py
hapi2/db/__init__.py
hapi2/db/models.py
hapi2/db/sqlalchemy/__init__.py
hapi2/db/sqlalchemy/base.py
hapi2/db/sqlalchemy/legacy.py
hapi2/db/sqlalchemy/models.py
hapi2/db/sqlalchemy/updaters.py
hapi2/db/sqlalchemy/mysql/__init__.py
hapi2/db/sqlalchemy/mysql/models.py
hapi2/db/sqlalchemy/sqlite/__init__.py
hapi2/db/sqlalchemy/sqlite/models.py
hapi2/format/__init__.py
hapi2/format/dispatch.py
hapi2/format/streamer.py
hapi2/format/utils.py
hapi2/format/hitran/__init__.py
hapi2/format/hitran/cia.py
hapi2/format/hitran/lbl.py
hapi2/format/hitran/xsc.py
hapi2/format/streamers/__init__.py
hapi2/format/streamers/dotpar.py
hapi2/format/streamers/json.py
hapi2/opacity/__init__.py
hapi2/opacity/models.py
hapi2/opacity/cia/__init__.py
hapi2/opacity/lbl/__init__.py
hapi2/opacity/lbl/calc_xsc.py
hapi2/opacity/lbl/numba/__init__.py
hapi2/opacity/lbl/numba/fast_abscoef.py
hapi2/opacity/lbl/numba/hum1_wei_numba.py
hapi2/opacity/lbl/numba/intrinsics.py
hapi2/opacity/lbl/numba/pCqSDHC_.py
hapi2/opacity/lbl/numba/sdv.py
hapi2/opacity/lbl/numba/settings.py
hapi2/opacity/lbl/numpy/__init__.py
hapi2/opacity/xsc/__init__.py
hapi2/profiling/__init__.py
hapi2/profiling/tictoc.py
hapi2/provenance/__init__.py
hapi2/provenance/conf.py
hapi2/provenance/libra2.py
hapi2/provenance/types.py
hapi2/utils/__init__.py
hapi2/utils/formula.py
hapi2/utils/tictoc.py
hapi2/utils/xsc.py
hapi2/web/__init__.py
hapi2/web/api.py
hitran_api2-0.2.dist-info/LICENSE.md
hitran_api2-0.2.dist-info/METADATA
hitran_api2-0.2.dist-info/WHEEL
hitran_api2-0.2.dist-info/top_level.txt
hitran_api2-0.2.dist-info/RECORD
